setuptools_svn/__init__.py
setuptools_svn/svn_utils.py
setuptools_svn-1.3.0.dist-info/LICENSE
setuptools_svn-1.3.0.dist-info/METADATA
setuptools_svn-1.3.0.dist-info/WHEEL
setuptools_svn-1.3.0.dist-info/entry_points.txt
setuptools_svn-1.3.0.dist-info/top_level.txt
setuptools_svn-1.3.0.dist-info/RECORD
